MANIFEST.in
README.md
setup.py
ovipositor/__init__.py
ovipositor/convert_YOURLS_SQLite_database_to_ovipositor_database.py
ovipositor.egg-info/PKG-INFO
ovipositor.egg-info/SOURCES.txt
ovipositor.egg-info/dependency_links.txt
ovipositor.egg-info/entry_points.txt
ovipositor.egg-info/not-zip-safe
ovipositor.egg-info/requires.txt
ovipositor.egg-info/top_level.txt
ovipositor/static/favicon.svg
ovipositor/templates/home.html