Metadata-Version: 1.0
Name: ovipositor
Version: 2018.6.21.1656
Summary: link-shortening website and database system
Home-page: https://github.com/wdbm/ovipositor
Author: Will Breaden Madden
Author-email: wbm@protonmail.ch
License: GPLv3
Platform: UNKNOWN
